quickumls_simstring/__init__.py
quickumls_simstring/_simstring.so
quickumls_simstring/simstring.py
medspacy_simstring-2.2a0.dist-info/METADATA
medspacy_simstring-2.2a0.dist-info/WHEEL
medspacy_simstring-2.2a0.dist-info/top_level.txt
medspacy_simstring-2.2a0.dist-info/RECORD
