Metadata-Version: 2.1
Name: medspacy-simstring
Version: 2.2a0
Summary: Clone of simstring for medspacy which was cloned from another clone designed to work with QuickUMLS. Original version here: http://chokkan.org/software/simstring/
Home-page: https://github.com/medspacy/simstring
Author: Naoaki Okazaki & Blink Health & Luca Soldaini & Kelly Peterson
Author-email: luca@ir.cs.georgetown.edu,kelly.peterson@hsc.utah.edu
